{
  "last_run": "2026-03-09T10:22:11.567Z",
  "converged": false,
  "iteration_count": 1,
  "final_residual_total": 121,
  "reverse_discovery_total": 309,
  "heatmap_total": 6132,
  "known_issues": [
    {
      "layer": "r_to_f",
      "residual": 3
    },
    {
      "layer": "f_to_c",
      "residual": 95
    },
    {
      "layer": "d_to_c",
      "residual": 23
    },
    {
      "layer": "c_to_r",
      "residual": 122
    },
    {
      "layer": "t_to_r",
      "residual": 173
    },
    {
      "layer": "d_to_r",
      "residual": 14
    },
    {
      "layer": "git_heatmap",
      "residual": 6132
    },
    {
      "layer": "git_history",
      "residual": 39
    },
    {
      "layer": "hazard_model",
      "residual": 9
    }
  ],
  "r_to_f_progress": {
    "total": 306,
    "covered": 0,
    "percentage": "0.0"
  }
}
