{
  "schema_version": "1",
  "phase": "v0.39-03",
  "created_at": "2026-03-18T18:17:27.039Z",
  "risk_level": "medium",
  "research": {
    "objective": "Phase v0.39-03 implements **Cycle 2: Solution Simulation**, the second half of dual-cycle formal reasoning. In Cycle 1 (v0.39-02), bugs validate and refine models. In Cycle 2, models validate fix idea",
    "constraints": "",
    "target_files": [],
    "confidence": "HIGH"
  },
  "plan": {
    "plan_path": ".planning/phases/v0.39-03-cycle-2-solution-simulation/v0.39-03-01-PLAN.md",
    "key_decisions": []
  }
}